{
  "generated_at": "2026-05-16T12:25:33Z",
  "skill_sync": [
    {
      "name": "lk-shopify-readonly",
      "src_exists": true,
      "dst_exists_before": true,
      "dst_exists_after": true,
      "skill_md_bytes": 32321,
      "references": 21
    },
    {
      "name": "lk-shopify-product-upload",
      "src_exists": true,
      "dst_exists_before": true,
      "dst_exists_after": true,
      "skill_md_bytes": 13768,
      "references": 2
    }
  ],
  "changed": [
    "MissionPages.tsx",
    "cron-jobs.ts",
    "domains.ts",
    "tenacitos.ts",
    "globals.css",
    "mission_control_ops_watchdog.py",
    "/opt/data/hermes_bruno_ingest/hermes-brain/areas/operacoes/rotinas/mission-control-v014-operationalization-2026-05-16.md"
  ]
}